datacamp_downloader/__init__.py
datacamp_downloader/constants.py
datacamp_downloader/datacamp_utils.py
datacamp_downloader/downloader.py
datacamp_downloader/helper.py
datacamp_downloader/session.py
datacamp_downloader/templates/course.py
datacamp_downloader/templates/exercise.py
datacamp_downloader/templates/lang.py
datacamp_downloader/templates/track.py
datacamp_downloader/templates/video.py
datacamp_downloader-3.3.dist-info/licenses/LICENSE
datacamp_downloader-3.3.dist-info/METADATA
datacamp_downloader-3.3.dist-info/WHEEL
datacamp_downloader-3.3.dist-info/entry_points.txt
datacamp_downloader-3.3.dist-info/top_level.txt
datacamp_downloader-3.3.dist-info/RECORD
