Metadata-Version: 2.4
Name: datacamp-downloader
Version: 3.3
Summary: Download your completed courses on Datacamp easily!
Home-page: https://github.com/TRoboto/datacamp-downloader
Author: Mohammad Al-Fetyani
Author-email: m4bh@hotmail.com
Project-URL: Bug Tracker, https://github.com/TRoboto/datacamp-downloader/issues
Classifier: Programming Language :: Python :: 3
Classifier: License :: OSI Approved :: MIT License
Classifier: Operating System :: OS Independent
Requires-Python: >=3.6
License-File: LICENSE
Requires-Dist: beautifulsoup4==4.13.5
Requires-Dist: requests==2.32.5
Requires-Dist: selenium==4.35.0
Requires-Dist: undetected-chromedriver==3.2.1
Requires-Dist: webdriver-manager==4.0.2
Requires-Dist: texttable==1.6.3
Requires-Dist: termcolor==1.1.0
Requires-Dist: colorama==0.4.4
Requires-Dist: tomd==0.1.3
Requires-Dist: typer==0.3.2
Requires-Dist: setuptools==80.9.0
Dynamic: author
Dynamic: author-email
Dynamic: classifier
Dynamic: description
Dynamic: description-content-type
Dynamic: home-page
Dynamic: license-file
Dynamic: project-url
Dynamic: requires-dist
Dynamic: requires-python
Dynamic: summary
